CompositeRecommenders/LSAEndowedSMR.py
CompositeRecommenders/SMR_to_LSA.py
CompositeRecommenders/__init__.py
CompositeRecommenders-0.0.1.dist-info/LICENSE
CompositeRecommenders-0.0.1.dist-info/METADATA
CompositeRecommenders-0.0.1.dist-info/WHEEL
CompositeRecommenders-0.0.1.dist-info/top_level.txt
CompositeRecommenders-0.0.1.dist-info/RECORD
